LICENSE
MANIFEST.in
README.rst
buildout.cfg
develop.cfg
requirements.txt
setup.py
version.txt
bob/__init__.py
bob.kaldi.egg-info/PKG-INFO
bob.kaldi.egg-info/SOURCES.txt
bob.kaldi.egg-info/dependency_links.txt
bob.kaldi.egg-info/entry_points.txt
bob.kaldi.egg-info/not-zip-safe
bob.kaldi.egg-info/requires.txt
bob.kaldi.egg-info/top_level.txt
bob/kaldi/__init__.py
bob/kaldi/cepstral.py
bob/kaldi/dnn.py
bob/kaldi/gmm.py
bob/kaldi/hmm.py
bob/kaldi/io.py
bob/kaldi/ivector.py
bob/kaldi/mfcc.py
bob/kaldi/test/__init__.py
bob/kaldi/test/test_dnn.py
bob/kaldi/test/test_extractor.py
bob/kaldi/test/test_gmm.py
bob/kaldi/test/test_hmm.py
bob/kaldi/test/test_ivector.py
bob/kaldi/test/test_plda_loader.py
bob/kaldi/test/data/feats-mobio.npy
bob/kaldi/test/data/ivector.ark
bob/kaldi/test/data/librivox.wav
bob/kaldi/test/data/plda
bob/kaldi/test/data/sample16k-cepstral-mfcc.txt
bob/kaldi/test/data/sample16k-cepstral-plp.txt
bob/kaldi/test/data/sample16k-dnn-vad.txt
bob/kaldi/test/data/sample16k-mfcc.txt
bob/kaldi/test/data/sample16k-posteriors.txt
bob/kaldi/test/data/sample16k-vad.txt
bob/kaldi/test/data/sample16k.ie
bob/kaldi/test/data/sample16k.ivector
bob/kaldi/test/data/sample16k.wav
bob/kaldi/test/data/test-mobio.ivector
bob/kaldi/test/dnn/ami.feature_transform.txt
bob/kaldi/test/dnn/ami.nnet.txt
bob/kaldi/test/dnn/ami.phones.txt
bob/kaldi/test/hmm/L.fst
bob/kaldi/test/hmm/sets.txt
bob/kaldi/test/hmm/topo.txt
bob/kaldi/test/hmm/words.txt
doc/conf.py
doc/guide.rst
doc/index.rst
doc/links.rst
doc/py_api.rst