Metadata-Version: 1.1
Name: bob.kaldi
Version: 1.3.0
Summary: Python Bindings for Kaldi
Home-page: https://gitlab.idiap.ch/bob/bob.kaldi
Author: Milos Cernak
Author-email: milo.cernak@idiap.ch
License: BSD
Platform: UNKNOWN
Classifier: Framework :: Bob
Classifier: Development Status :: 4 - Beta
Classifier: Intended Audience :: Developers
Classifier: License :: OSI Approved :: BSD License
Classifier: Natural Language :: English
Classifier: Programming Language :: Python
Classifier: Programming Language :: Python :: 3
Classifier: Topic :: Scientific/Engineering :: Artificial Intelligence
Classifier: Topic :: Software Development :: Libraries :: Python Modules
